neutron_plugin_pluribus-3.0.dist-info/DESCRIPTION.rst
neutron_plugin_pluribus-3.0.dist-info/entry_points.txt
neutron_plugin_pluribus-3.0.dist-info/METADATA
neutron_plugin_pluribus-3.0.dist-info/metadata.json
neutron_plugin_pluribus-3.0.dist-info/RECORD
neutron_plugin_pluribus-3.0.dist-info/top_level.txt
neutron_plugin_pluribus-3.0.dist-info/WHEEL
pluribus/__init__.py
pluribus/plugins/__init__.py
pluribus/plugins/pn_plugin.py
pluribus/plugins/ml2/__init__.py
pluribus/plugins/ml2/config.py
pluribus/plugins/ml2/mech_pluribus.py
